bytedance_ad_data_stats_util/__init__.py
bytedance_ad_data_stats_util-0.0.1.dist-info/METADATA
bytedance_ad_data_stats_util-0.0.1.dist-info/WHEEL
bytedance_ad_data_stats_util-0.0.1.dist-info/top_level.txt
bytedance_ad_data_stats_util-0.0.1.dist-info/RECORD
