Metadata-Version: 2.1
Name: bytedance-ad-data-stats-util
Version: 0.0.1
Summary: A simple package named bytedance_ad_data_stats_util
Home-page: https://github.com/artifact/bytedance_ad_data_stats_util.git
Author: artifact
Author-email: artifact@example.com
License: UNKNOWN
Platform: UNKNOWN
Classifier: Programming Language :: Python :: 3
Classifier: License :: OSI Approved :: MIT License
Classifier: Operating System :: OS Independent
